exiftoolpy/__init__.py
exiftoolpy/exiftool
exiftoolpy/exiftool-13.10/Changes
exiftoolpy/exiftool-13.10/MANIFEST
exiftoolpy/exiftool-13.10/META.json
exiftoolpy/exiftool-13.10/META.yml
exiftoolpy/exiftool-13.10/MYMETA.json
exiftoolpy/exiftool-13.10/MYMETA.yml
exiftoolpy/exiftool-13.10/Makefile
exiftoolpy/exiftool-13.10/Makefile.PL
exiftoolpy/exiftool-13.10/README
exiftoolpy/exiftool-13.10/build_geolocation
exiftoolpy/exiftool-13.10/perl-Image-ExifTool.spec
exiftoolpy/exiftool-13.10/pm_to_blib
exiftoolpy/exiftool-13.10/arg_files/exif2iptc.args
exiftoolpy/exiftool-13.10/arg_files/exif2xmp.args
exiftoolpy/exiftool-13.10/arg_files/gps2xmp.args
exiftoolpy/exiftool-13.10/arg_files/iptc2exif.args
exiftoolpy/exiftool-13.10/arg_files/iptc2xmp.args
exiftoolpy/exiftool-13.10/arg_files/iptcCore.args
exiftoolpy/exiftool-13.10/arg_files/pdf2xmp.args
exiftoolpy/exiftool-13.10/arg_files/xmp2exif.args
exiftoolpy/exiftool-13.10/arg_files/xmp2gps.args
exiftoolpy/exiftool-13.10/arg_files/xmp2iptc.args
exiftoolpy/exiftool-13.10/arg_files/xmp2pdf.args
exiftoolpy/exiftool-13.10/blib/arch/.exists
exiftoolpy/exiftool-13.10/blib/arch/auto/Image/ExifTool/.exists
exiftoolpy/exiftool-13.10/blib/bin/.exists
exiftoolpy/exiftool-13.10/blib/lib/File/RandomAccess.pm
exiftoolpy/exiftool-13.10/blib/lib/File/RandomAccess.pod
exiftoolpy/exiftool-13.10/blib/lib/Image/.exists
exiftoolpy/exiftool-13.10/blib/lib/Image/ExifTool.pm
exiftoolpy/exiftool-13.10/blib/lib/Image/ExifTool.pod
exiftoolpy/exiftool-13.10/blib/lib/Image/ExifTool/7Z.pm
exiftoolpy/exiftool-13.10/blib/lib/Image/ExifTool/AAC.pm
exiftoolpy/exiftool-13.10/blib/lib/Image/ExifTool/AES.pm
exiftoolpy/exiftool-13.10/blib/lib/Image/ExifTool/AFCP.pm
exiftoolpy/exiftool-13.10/blib/lib/Image/ExifTool/AIFF.pm
exiftoolpy/exiftool-13.10/blib/lib/Image/ExifTool/APE.pm
exiftoolpy/exiftool-13.10/blib/lib/Image/ExifTool/APP12.pm
exiftoolpy/exiftool-13.10/blib/lib/Image/ExifTool/ASF.pm
exiftoolpy/exiftool-13.10/blib/lib/Image/ExifTool/Apple.pm
exiftoolpy-1.8.dist-info/METADATA
exiftoolpy-1.8.dist-info/WHEEL
exiftoolpy-1.8.dist-info/top_level.txt
exiftoolpy-1.8.dist-info/RECORD
