Metadata-Version: 2.1
Name: exiftoolpy
Version: 1.8
Summary: exiftoolpy
Home-page: https://github.com/lababidi/exiftoolpy
Author: Mahmoud Lababidi
Author-email: mahmoud@mahmoud.one
